flask_log_request_id/__init__.py
flask_log_request_id/ctx_fetcher.py
flask_log_request_id/filters.py
flask_log_request_id/parser.py
flask_log_request_id/request_id.py
flask_log_request_id/extras/__init__.py
flask_log_request_id/extras/celery.py
Flask_3_Log_Request_ID-0.11.1.dist-info/LICENSE.md
Flask_3_Log_Request_ID-0.11.1.dist-info/METADATA
Flask_3_Log_Request_ID-0.11.1.dist-info/WHEEL
Flask_3_Log_Request_ID-0.11.1.dist-info/top_level.txt
Flask_3_Log_Request_ID-0.11.1.dist-info/RECORD
