Metadata-Version: 2.1
Name: Flask-3-Log-Request-ID
Version: 0.11.1
Summary: Flask extension that can parse and handle multiple types of request-id sent by request processors like Amazon ELB, Heroku or any multi-tier infrastructure as the one used for microservices.
Home-page: http://github.com/ritwickdey/flask-log-request-id
Author: Ritwick Dey
Author-email: ritwickdey@outlook.com
Maintainer: Ritwick Dey
Maintainer-email: ritwickdey@outlook.com
License: MIT
Platform: any
Classifier: Environment :: Web Environment
Classifier: Intended Audience :: Developers
Classifier: License :: OSI Approved :: MIT License
Classifier: Operating System :: OS Independent
Classifier: Programming Language :: Python
Classifier: Programming Language :: Python :: 3
Classifier: Topic :: Software Development :: Libraries :: Python Modules
License-File: LICENSE.md
Requires-Dist: Flask >=0.8
Provides-Extra: test
Requires-Dist: pynose ; extra == 'test'
Requires-Dist: flake8 ; extra == 'test'
Requires-Dist: mock ==2.0.0 ; extra == 'test'
Requires-Dist: coverage ~=4.5.4 ; extra == 'test'
Requires-Dist: celery ; extra == 'test'
